ScapyLibrary/ScapyLibrary.xml
ScapyLibrary/__init__.py
ScapyLibrary/layerDoc.py
ScapyLibrary/version.py
ScapyLibrary/keywords/__init__.py
ScapyLibrary/keywords/layers.py
ScapyLibrary/keywords/pcap.py
ScapyLibrary/keywords/scapyfunctions.py
ScapyLibrary/keywords/sendrecv.py
ScapyLibrary/utils/__init__.py
ScapyLibrary/utils/_scapy.py
ScapyLibrary/utils/baseclass.py
robotframework_ScapyLibrary-0.1.6.dist-info/DESCRIPTION.rst
robotframework_ScapyLibrary-0.1.6.dist-info/METADATA
robotframework_ScapyLibrary-0.1.6.dist-info/RECORD
robotframework_ScapyLibrary-0.1.6.dist-info/WHEEL
robotframework_ScapyLibrary-0.1.6.dist-info/metadata.json
robotframework_ScapyLibrary-0.1.6.dist-info/top_level.txt
