Metadata-Version: 2.0
Name: robotframework-ScapyLibrary
Version: 0.1.6
Summary: Scapy library for Robot Framework
Home-page: https://github.com/rainmanwy/robotframework-ScapyLibrary
Author: Wang Yang
Author-email: wang_yang1980@hotmail.com
License: Apache License 2.0
Keywords: robotframework testing testautomation scapy network protocol
Platform: any
Classifier: Operating System :: OS Independent
Classifier: Programming Language :: Python
Classifier: Topic :: Software Development :: Testing
Requires-Dist: scapy (>=2.3.2)
